Workbook
Name Slicer_Category: #N/A
Name Slicer_Region: #N/A
Name Slicer_Segment: #N/A
Name Slicer_Ship_Mode: #N/A
Name Slicer_Years: #N/A

Sheet Orders
A1: Row ID | B1: Order ID | C1: Order Date | D1: Ship Date | E1: Ship Mode | F1: Customer ID | G1: Customer Name | H1: Segment | I1: Country | J1: City | K1: State | L1: Postal Code | M1: Region | N1: Product ID | O1: Category | P1: Sub-Category | Q1: Product Name | R1: Sales | S1: Quantity | T1: Discount | U1: Profit | V1: Profit Margin
A2: 1 | B2: CA-2016-152156 | C2: 42682 | D2: 42685 | E2: Second Class | F2: CG-12520 | G2: Claire Gute | H2: Consumer | I2: United States | J2: Henderson | K2: Kentucky | L2: 42420 | M2: South | N2: FUR-BO-10001798 | O2: Furniture | P2: Bookcases | Q2: Bush Somerset Collection Bookcase | R2: 261.96 | S2: 2 | T2: 0 | U2: 41.9136 | V2: =U2/R2 -> 0.16
A3: 2 | B3: CA-2016-152156 | C3: 42682 | D3: 42685 | E3: Second Class | F3: CG-12520 | G3: Claire Gute | H3: Consumer | I3: United States | J3: Henderson | K3: Kentucky | L3: 42420 | M3: South | N3: FUR-CH-10000454 | O3: Furniture | P3: Chairs | Q3: Hon Deluxe Fabric Upholstered Stacking Chairs, Rounded Back | R3: 731.94 | S3: 3 | T3: 0 | U3: 219.582 | V3: =U3/R3 -> 0.3
A4: 3 | B4: CA-2016-138688 | C4: 42533 | D4: 42537 | E4: Second Class | F4: DV-13045 | G4: Darrin Van Huff | H4: Corporate | I4: United States | J4: Los Angeles | K4: California | L4: 90036 | M4: West | N4: OFF-LA-10000240 | O4: Office Supplies | P4: Labels | Q4: Self-Adhesive Address Labels for Typewriters by Universal | R4: 14.62 | S4: 2 | T4: 0 | U4: 6.8714 | V4: =U4/R4 -> 0.47
A5: 4 | B5: US-2015-108966 | C5: 42288 | D5: 42295 | E5: Standard Class | F5: SO-20335 | G5: Sean O'Donnell | H5: Consumer | I5: United States | J5: Fort Lauderdale | K5: Florida | L5: 33311 | M5: South | N5: FUR-TA-10000577 | O5: Furniture | P5: Tables | Q5: Bretford CR4500 Series Slim Rectangular Table | R5: 957.5775 | S5: 5 | T5: 0.45 | U5: -383.031 | V5: =U5/R5 -> -0.4
A6: 5 | B6: US-2015-108966 | C6: 42288 | D6: 42295 | E6: Standard Class | F6: SO-20335 | G6: Sean O'Donnell | H6: Consumer | I6: United States | J6: Fort Lauderdale | K6: Florida | L6: 33311 | M6: South | N6: OFF-ST-10000760 | O6: Office Supplies | P6: Storage | Q6: Eldon Fold 'N Roll Cart System | R6: 22.368 | S6: 2 | T6: 0.2 | U6: 2.5164 | V6: =U6/R6 -> 0.1125
A7: 6 | B7: CA-2014-115812 | C7: 41799 | D7: 41804 | E7: Standard Class | F7: BH-11710 | G7: Brosina Hoffman | H7: Consumer | I7: United States | J7: Los Angeles | K7: California | L7: 90032 | M7: West | N7: FUR-FU-10001487 | O7: Furniture | P7: Furnishings | Q7: Eldon Expressions Wood and Plastic Desk Accessories, Cherry Wood | R7: 48.86 | S7: 7 | T7: 0 | U7: 14.1694 | V7: =U7/R7 -> 0.29
A8: 7 | B8: CA-2014-115812 | C8: 41799 | D8: 41804 | E8: Standard Class | F8: BH-11710 | G8: Brosina Hoffman | H8: Consumer | I8: United States | J8: Los Angeles | K8: California | L8: 90032 | M8: West | N8: OFF-AR-10002833 | O8: Office Supplies | P8: Art | Q8: Newell 322 | R8: 7.28 | S8: 4 | T8: 0 | U8: 1.9656 | V8: =U8/R8 -> 0.27
A9: 8 | B9: CA-2014-115812 | C9: 41799 | D9: 41804 | E9: Standard Class | F9: BH-11710 | G9: Brosina Hoffman | H9: Consumer | I9: United States | J9: Los Angeles | K9: California | L9: 90032 | M9: West | N9: TEC-PH-10002275 | O9: Technology | P9: Phones | Q9: Mitel 5320 IP Phone VoIP phone | R9: 907.152 | S9: 6 | T9: 0.2 | U9: 90.7152 | V9: =U9/R9 -> 0.1
A10: 9 | B10: CA-2014-115812 | C10: 41799 | D10: 41804 | E10: Standard Class | F10: BH-11710 | G10: Brosina Hoffman | H10: Consumer | I10: United States | J10: Los Angeles | K10: California | L10: 90032 | M10: West | N10: OFF-BI-10003910 | O10: Office Supplies | P10: Binders | Q10: DXL Angle-View Binders with Locking Rings by Samsill | R10: 18.504 | S10: 3 | T10: 0.2 | U10: 5.7825 | V10: =U10/R10 -> 0.3125
A11: 10 | B11: CA-2014-115812 | C11: 41799 | D11: 41804 | E11: Standard Class | F11: BH-11710 | G11: Brosina Hoffman | H11: Consumer | I11: United States | J11: Los Angeles | K11: California | L11: 90032 | M11: West | N11: OFF-AP-10002892 | O11: Office Supplies | P11: Appliances | Q11: Belkin F5C206VTEL 6 Outlet Surge | R11: 114.9 | S11: 5 | T11: 0 | U11: 34.47 | V11: =U11/R11 -> 0.3
A12: 11 | B12: CA-2014-115812 | C12: 41799 | D12: 41804 | E12: Standard Class | F12: BH-11710 | G12: Brosina Hoffman | H12: Consumer | I12: United States | J12: Los Angeles | K12: California | L12: 90032 | M12: West | N12: FUR-TA-10001539 | O12: Furniture | P12: Tables | Q12: Chromcraft Rectangular Conference Tables | R12: 1706.184 | S12: 9 | T12: 0.2 | U12: 85.3092 | V12: =U12/R12 -> 0.05
A13: 12 | B13: CA-2014-115812 | C13: 41799 | D13: 41804 | E13: Standard Class | F13: BH-11710 | G13: Brosina Hoffman | H13: Consumer | I13: United States | J13: Los Angeles | K13: California | L13: 90032 | M13: West | N13: TEC-PH-10002033 | O13: Technology | P13: Phones | Q13: Konftel 250 Conference phone - Charcoal black | R13: 911.424 | S13: 4 | T13: 0.2 | U13: 68.3568 | V13: =U13/R13 -> 0.075
... A2235: 2234 | B2235: CA-2015-123232 | C2235: 42352 | D2235: 42354 | E2235: Second Class | F2235: DJ-13630 | G2235: Doug Jacobs | H2235: Consumer | I2235: United States | J2235: Portland | K2235: Oregon | L2235: 97206 | M2235: West | N2235: TEC-PH-10001051 | O2235: Technology | P2235: Phones | Q2235: HTC One | R2235: 319.968 | S2235: 4 | T2235: 0.2 | U2235: 35.9964 | V2235: =U2235/R2235 -> 0.1125
A2236: 2235 | B2236: CA-2017-104066 | C2236: 43074 | D2236: 43079 | E2236: Standard Class | F2236: QJ-19255 | G2236: Quincy Jones | H2236: Corporate | I2236: United States | J2236: Burlington | K2236: Vermont | L2236: 05408 | M2236: East | N2236: TEC-AC-10001013 | O2236: Technology | P2236: Accessories | Q2236: Logitech ClearChat Comfort/USB Headset H390 | R2236: 205.03 | S2236: 7 | T2236: 0 | U2236: 67.6599 | V2236: =U2236/R2236 -> 0.33
A2237: 2236 | B2237: CA-2015-145849 | C2237: 42262 | D2237: 42264 | E2237: Second Class | F2237: CT-11995 | G2237: Carol Triggs | H2237: Consumer | I2237: United States | J2237: Indianapolis | K2237: Indiana | L2237: 46203 | M2237: Central | N2237: OFF-ST-10000025 | O2237: Office Supplies | P2237: Storage | Q2237: Fellowes Stor/Drawer Steel Plus Storage Drawers | R2237: 190.86 | S2237: 2 | T2237: 0 | U2237: 11.4516 | V2237: =U2237/R2237 -> 0.06
A2238: 2237 | B2238: CA-2015-145849 | C2238: 42262 | D2238: 42264 | E2238: Second Class | F2238: CT-11995 | G2238: Carol Triggs | H2238: Consumer | I2238: United States | J2238: Indianapolis | K2238: Indiana | L2238: 46203 | M2238: Central | N2238: OFF-AR-10000817 | O2238: Office Supplies | P2238: Art | Q2238: Manco Dry-Lighter Erasable Highlighter | R2238: 24.32 | S2238: 8 | T2238: 0 | U2238: 8.2688 | V2238: =U2238/R2238 -> 0.34
A2239: 2238 | B2239: CA-2016-122322 | C2239: 42566 | D2239: 42572 | E2239: Standard Class | F2239: RH-19510 | G2239: Rick Huthwaite | H2239: Home Office | I2239: United States | J2239: Provo | K2239: Utah | L2239: 84604 | M2239: West | N2239: OFF-SU-10000952 | O2239: Office Supplies | P2239: Supplies | Q2239: Fiskars Home & Office Scissors | R2239: 44.4 | S2239: 5 | T2239: 0 | U2239: 12.432 | V2239: =U2239/R2239 -> 0.28
A2240: 2239 | B2240: CA-2017-166849 | C2240: 42845 | D2240: 42851 | E2240: Standard Class | F2240: SJ-20125 | G2240: Sanjit Jacobs | H2240: Home Office | I2240: United States | J2240: Chicago | K2240: Illinois | L2240: 60610 | M2240: Central | N2240: FUR-FU-10004597 | O2240: Furniture | P2240: Furnishings | Q2240: Eldon Cleatmat Chair Mats for Medium Pile Carpets | R2240: 44.4 | S2240: 2 | T2240: 0.6 | U2240: -52.17 | V2240: =U2240/R2240 -> -1.175
A2241: 2240 | B2241: CA-2016-146633 | C2241: 42689 | D2241: 42691 | E2241: Second Class | F2241: TG-21310 | G2241: Toby Gnade | H2241: Consumer | I2241: United States | J2241: Los Angeles | K2241: California | L2241: 90049 | M2241: West | N2241: OFF-BI-10003527 | O2241: Office Supplies | P2241: Binders | Q2241: Fellowes PB500 Electric Punch Plastic Comb Binding Machine with Manual Bind | R2241: 1016.792 | S2241: 1 | T2241: 0.2 | U2241: 381.297 | V2241: =U2241/R2241 -> 0.375
A2242: 2241 | B2242: CA-2016-146633 | C2242: 42689 | D2242: 42691 | E2242: Second Class | F2242: TG-21310 | G2242: Toby Gnade | H2242: Consumer | I2242: United States | J2242: Los Angeles | K2242: California | L2242: 90049 | M2242: West | N2242: OFF-BI-10002982 | O2242: Office Supplies | P2242: Binders | Q2242: Avery Self-Adhesive Photo Pockets for Polaroid Photos | R2242: 38.136 | S2242: 7 | T2242: 0.2 | U2242: 13.3476 | V2242: =U2242/R2242 -> 0.35
A2243: 2242 | B2243: US-2016-126893 | C2243: 42700 | D2243: 42705 | E2243: Standard Class | F2243: CT-11995 | G2243: Carol Triggs | H2243: Consumer | I2243: United States | J2243: Philadelphia | K2243: Pennsylvania | L2243: 19134 | M2243: East | N2243: TEC-PH-10004165 | O2243: Technology | P2243: Phones | Q2243: Mitel MiVoice 5330e IP Phone | R2243: 494.982 | S2243: 3 | T2243: 0.4 | U2243: -115.4958 | V2243: =U2243/R2243 -> -0.23333333
A2244: 2243 | B2244: CA-2017-103380 | C2244: 43060 | D2244: 43064 | E2244: Standard Class | F2244: BF-11005 | G2244: Barry Franz | H2244: Home Office | I2244: United States | J2244: Pasadena | K2244: California | L2244: 91104 | M2244: West | N2244: OFF-ST-10003442 | O2244: Office Supplies | P2244: Storage | Q2244: Eldon Portable Mobile Manager | R2244: 56.56 | S2244: 2 | T2244: 0 | U2244: 15.2712 | V2244: =U2244/R2244 -> 0.27
A2245: 2244 | B2245: CA-2017-103380 | C2245: 43060 | D2245: 43064 | E2245: Standard Class | F2245: BF-11005 | G2245: Barry Franz | H2245: Home Office | I2245: United States | J2245: Pasadena | K2245: California | L2245: 91104 | M2245: West | N2245: OFF-AR-10003856 | O2245: Office Supplies | P2245: Art | Q2245: Newell 344 | R2245: 5.56 | S2245: 2 | T2245: 0 | U2245: 1.4456 | V2245: =U2245/R2245 -> 0.26
A2246: 2245 | B2246: CA-2017-103380 | C2246: 43060 | D2246: 43064 | E2246: Standard Class | F2246: BF-11005 | G2246: Barry Franz | H2246: Home Office | I2246: United States | J2246: Pasadena | K2246: California | L2246: 91104 | M2246: West | N2246: OFF-FA-10004248 | O2246: Office Supplies | P2246: Fasteners | Q2246: Advantus T-Pin Paper Clips | R2246: 9.02 | S2246: 2 | T2246: 0 | U2246: 3.5178 | V2246: =U2246/R2246 -> 0.39
A2247: 2246 | B2247: CA-2017-103380 | C2247: 43060 | D2247: 43064 | E2247: Standard Class | F2247: BF-11005 | G2247: Barry Franz | H2247: Home Office | I2247: United States | J2247: Pasadena | K2247: California | L2247: 91104 | M2247: West | N2247: OFF-AP-10001492 | O2247: Office Supplies | P2247: Appliances | Q2247: Acco Six-Outlet Power Strip, 4' Cord Length | R2247: 8.62 | S2247: 1 | T2247: 0 | U2247: 2.2412 | V2247: =U2247/R2247 -> 0.26
A2248: 2247 | B2248: CA-2017-103380 | C2248: 43060 | D2248: 43064 | E2248: Standard Class | F2248: BF-11005 | G2248: Barry Franz | H2248: Home Office | I2248: United States | J2248: Pasadena | K2248: California | L2248: 91104 | M2248: West | N2248: TEC-PH-10004165 | O2248: Technology | P2248: Phones | Q2248: Mitel MiVoice 5330e IP Phone | R2248: 659.976 | S2248: 3 | T2248: 0.2 | U2248: 49.4982 | V2248: =U2248/R2248 -> 0.075
... A5275: 5274 | B5275: US-2016-158309 | C5275: 42700 | D5275: 42703 | E5275: First Class | F5275: PA-19060 | G5275: Pete Armstrong | H5275: Home Office | I5275: United States | J5275: Miami | K5275: Florida | L5275: 33142 | M5275: South | N5275: OFF-BI-10000145 | O5275: Office Supplies | P5275: Binders | Q5275: Zipper Ring Binder Pockets | R5275: 3.744 | S5275: 4 | T5275: 0.7 | U5275: -2.6208 | V5275: =U5275/R5275 -> -0.7
A5276: 5275 | B5276: CA-2015-162887 | C5276: 42315 | D5276: 42317 | E5276: Second Class | F5276: SV-20785 | G5276: Stewart Visinsky | H5276: Consumer | I5276: United States | J5276: Burlington | K5276: Vermont | L5276: 05408 | M5276: East | N5276: FUR-CH-10000595 | O5276: Furniture | P5276: Chairs | Q5276: Safco Contoured Stacking Chairs | R5276: 715.2 | S5276: 3 | T5276: 0 | U5276: 178.8 | V5276: =U5276/R5276 -> 0.25
A5277: 5276 | B5277: CA-2017-147333 | C5277: 43083 | D5277: 43089 | E5277: Standard Class | F5277: KL-16555 | G5277: Kelly Lampkin | H5277: Corporate | I5277: United States | J5277: Fayetteville | K5277: Arkansas | L5277: 72701 | M5277: South | N5277: TEC-AC-10004469 | O5277: Technology | P5277: Accessories | Q5277: Microsoft Sculpt Comfort Mouse | R5277: 159.8 | S5277: 4 | T5277: 0 | U5277: 70.312 | V5277: =U5277/R5277 -> 0.44
A5278: 5277 | B5278: CA-2017-147333 | C5278: 43083 | D5278: 43089 | E5278: Standard Class | F5278: KL-16555 | G5278: Kelly Lampkin | H5278: Corporate | I5278: United States | J5278: Fayetteville | K5278: Arkansas | L5278: 72701 | M5278: South | N5278: TEC-AC-10003038 | O5278: Technology | P5278: Accessories | Q5278: Kingston Digital DataTraveler 16GB USB 2.0 | R5278: 44.75 | S5278: 5 | T5278: 0 | U5278: 8.5025 | V5278: =U5278/R5278 -> 0.19
A5279: 5278 | B5279: CA-2014-113859 | C5279: 41895 | D5279: 41899 | E5279: Standard Class | F5279: BC-11125 | G5279: Becky Castell | H5279: Home Office | I5279: United States | J5279: Odessa | K5279: Texas | L5279: 79762 | M5279: Central | N5279: FUR-CH-10004698 | O5279: Furniture | P5279: Chairs | Q5279: Padded Folding Chairs, Black, 4/Carton | R5279: 340.116 | S5279: 6 | T5279: 0.3 | U5279: -9.7176 | V5279: =U5279/R5279 -> -0.028571429
A5280: 5279 | B5280: CA-2014-159681 | C5280: 41980 | D5280: 41986 | E5280: Standard Class | F5280: PO-18850 | G5280: Patrick O'Brill | H5280: Consumer | I5280: United States | J5280: Virginia Beach | K5280: Virginia | L5280: 23464 | M5280: South | N5280: OFF-PA-10003641 | O5280: Office Supplies | P5280: Paper | Q5280: Xerox 1909 | R5280: 105.52 | S5280: 4 | T5280: 0 | U5280: 48.5392 | V5280: =U5280/R5280 -> 0.46
A5281: 5280 | B5281: US-2017-104094 | C5281: 42985 | D5281: 42989 | E5281: Standard Class | F5281: AG-10675 | G5281: Anna Gayman | H5281: Consumer | I5281: United States | J5281: Milwaukee | K5281: Wisconsin | L5281: 53209 | M5281: Central | N5281: TEC-AC-10002134 | O5281: Technology | P5281: Accessories | Q5281: Rosewill 107 Normal Keys USB Wired Standard Keyboard | R5281: 13.48 | S5281: 1 | T5281: 0 | U5281: 1.8872 | V5281: =U5281/R5281 -> 0.14
A5282: 5281 | B5282: CA-2017-152709 | C5282: 43015 | D5282: 43020 | E5282: Standard Class | F5282: DB-13210 | G5282: Dean Braden | H5282: Consumer | I5282: United States | J5282: Detroit | K5282: Michigan | L5282: 48234 | M5282: Central | N5282: OFF-ST-10001837 | O5282: Office Supplies | P5282: Storage | Q5282: SAFCO Mobile Desk Side File, Wire Frame | R5282: 85.52 | S5282: 2 | T5282: 0 | U5282: 22.2352 | V5282: =U5282/R5282 -> 0.26
A5283: 5282 | B5283: CA-2015-105158 | C5283: 42252 | D5283: 42257 | E5283: Standard Class | F5283: SP-20860 | G5283: Sung Pak | H5283: Corporate | I5283: United States | J5283: Rochester | K5283: Minnesota | L5283: 55901 | M5283: Central | N5283: FUR-FU-10001706 | O5283: Furniture | P5283: Furnishings | Q5283: Longer-Life Soft White Bulbs | R5283: 6.16 | S5283: 2 | T5283: 0 | U5283: 2.9568 | V5283: =U5283/R5283 -> 0.48
A5284: 5283 | B5284: CA-2015-105158 | C5284: 42252 | D5284: 42257 | E5284: Standard Class | F5284: SP-20860 | G5284: Sung Pak | H5284: Corporate | I5284: United States | J5284: Rochester | K5284: Minnesota | L5284: 55901 | M5284: Central | N5284: OFF-PA-10001970 | O5284: Office Supplies | P5284: Paper | Q5284: Xerox 1881 | R5284: 36.84 | S5284: 3 | T5284: 0 | U5284: 17.3148 | V5284: =U5284/R5284 -> 0.47
A5285: 5284 | B5285: CA-2014-133424 | C5285: 41728 | D5285: 41733 | E5285: Standard Class | F5285: Dl-13600 | G5285: Dorris liebe | H5285: Corporate | I5285: United States | J5285: Seattle | K5285: Washington | L5285: 98105 | M5285: West | N5285: OFF-ST-10002957 | O5285: Office Supplies | P5285: Storage | Q5285: Sterilite Show Offs Storage Containers | R5285: 15.84 | S5285: 3 | T5285: 0 | U5285: 0 | V5285: =U5285/R5285 -> 0
A5286: 5285 | B5286: CA-2014-133424 | C5286: 41728 | D5286: 41733 | E5286: Standard Class | F5286: Dl-13600 | G5286: Dorris liebe | H5286: Corporate | I5286: United States | J5286: Seattle | K5286: Washington | L5286: 98105 | M5286: West | N5286: OFF-LA-10002312 | O5286: Office Supplies | P5286: Labels | Q5286: Avery 490 | R5286: 44.4 | S5286: 3 | T5286: 0 | U5286: 22.2 | V5286: =U5286/R5286 -> 0.5
A5287: 5286 | B5287: CA-2017-105991 | C5287: 42860 | D5287: 42861 | E5287: First Class | F5287: LH-17020 | G5287: Lisa Hazard | H5287: Consumer | I5287: United States | J5287: Louisville | K5287: Colorado | L5287: 80027 | M5287: West | N5287: OFF-EN-10002600 | O5287: Office Supplies | P5287: Envelopes | Q5287: Redi-Strip #10 Envelopes, 4 1/8 x 9 1/2 | R5287: 21.24 | S5287: 9 | T5287: 0.2 | U5287: 7.434 | V5287: =U5287/R5287 -> 0.35
A5288: 5287 | B5288: CA-2017-105991 | C5288: 42860 | D5288: 42861 | E5288: First Class | F5288: LH-17020 | G5288: Lisa Hazard | H5288: Consumer | I5288: United States | J5288: Louisville | K5288: Colorado | L5288: 80027 | M5288: West | N5288: OFF-BI-10003274 | O5288: Office Supplies | P5288: Binders | Q5288: Avery Durable Slant Ring Binders, No Labels | R5288: 9.552 | S5288: 8 | T5288: 0.7 | U5288: -7.3232 | V5288: =U5288/R5288 -> -0.76666667
... A8799: 8798 | B8799: CA-2016-106397 | C8799: 42558 | D8799: 42564 | E8799: Standard Class | F8799: MJ-17740 | G8799: Max Jones | H8799: Consumer | I8799: United States | J8799: Orem | K8799: Utah | L8799: 84057 | M8799: West | N8799: OFF-AR-10004602 | O8799: Office Supplies | P8799: Art | Q8799: Boston KS Multi-Size Manual Pencil Sharpener | R8799: 45.98 | S8799: 2 | T8799: 0 | U8799: 12.8744 | V8799: =U8799/R8799 -> 0.28
A8800: 8799 | B8800: US-2016-150140 | C8800: 42466 | D8800: 42470 | E8800: Standard Class | F8800: VM-21685 | G8800: Valerie Mitchum | H8800: Home Office | I8800: United States | J8800: Burlington | K8800: Vermont | L8800: 05408 | M8800: East | N8800: TEC-PH-10002555 | O8800: Technology | P8800: Phones | Q8800: Nortel Meridian M5316 Digital phone | R8800: 1294.75 | S8800: 5 | T8800: 0 | U8800: 336.635 | V8800: =U8800/R8800 -> 0.26
A8801: 8800 | B8801: CA-2014-116666 | C8801: 41767 | D8801: 41769 | E8801: First Class | F8801: KT-16480 | G8801: Kean Thornton | H8801: Consumer | I8801: United States | J8801: Philadelphia | K8801: Pennsylvania | L8801: 19134 | M8801: East | N8801: TEC-CO-10001449 | O8801: Technology | P8801: Copiers | Q8801: Hewlett Packard LaserJet 3310 Copier | R8801: 1799.97 | S8801: 5 | T8801: 0.4 | U8801: 239.996 | V8801: =U8801/R8801 -> 0.13333333
A8802: 8801 | B8802: CA-2017-148992 | C8802: 43062 | D8802: 43066 | E8802: Standard Class | F8802: CS-12250 | G8802: Chris Selesnick | H8802: Corporate | I8802: United States | J8802: Chicago | K8802: Illinois | L8802: 60623 | M8802: Central | N8802: OFF-PA-10004285 | O8802: Office Supplies | P8802: Paper | Q8802: Xerox 1959 | R8802: 10.688 | S8802: 2 | T8802: 0.2 | U8802: 3.7408 | V8802: =U8802/R8802 -> 0.35
A8803: 8802 | B8803: CA-2016-140935 | C8803: 42684 | D8803: 42686 | E8803: First Class | F8803: AB-10015 | G8803: Aaron Bergman | H8803: Consumer | I8803: United States | J8803: Oklahoma City | K8803: Oklahoma | L8803: 73120 | M8803: Central | N8803: TEC-PH-10000562 | O8803: Technology | P8803: Phones | Q8803: Samsung Convoy 3 | R8803: 221.98 | S8803: 2 | T8803: 0 | U8803: 62.1544 | V8803: =U8803/R8803 -> 0.28
A8804: 8803 | B8804: CA-2016-140935 | C8804: 42684 | D8804: 42686 | E8804: First Class | F8804: AB-10015 | G8804: Aaron Bergman | H8804: Consumer | I8804: United States | J8804: Oklahoma City | K8804: Oklahoma | L8804: 73120 | M8804: Central | N8804: FUR-BO-10003966 | O8804: Furniture | P8804: Bookcases | Q8804: Sauder Facets Collection Library, Sky Alder Finish | R8804: 341.96 | S8804: 2 | T8804: 0 | U8804: 54.7136 | V8804: =U8804/R8804 -> 0.16
A8805: 8804 | B8805: CA-2014-157644 | C8805: 42004 | D8805: 42005 | E8805: First Class | F8805: AH-10030 | G8805: Aaron Hawkins | H8805: Corporate | I8805: United States | J8805: New York City | K8805: New York | L8805: 10035 | M8805: East | N8805: TEC-AC-10003614 | O8805: Technology | P8805: Accessories | Q8805: Verbatim 25 GB 6x Blu-ray Single Layer Recordable Disc, 10/Pack | R8805: 34.77 | S8805: 3 | T8805: 0 | U8805: 11.4741 | V8805: =U8805/R8805 -> 0.33
A8806: 8805 | B8806: CA-2014-157644 | C8806: 42004 | D8806: 42005 | E8806: First Class | F8806: AH-10030 | G8806: Aaron Hawkins | H8806: Corporate | I8806: United States | J8806: New York City | K8806: New York | L8806: 10035 | M8806: East | N8806: OFF-LA-10003148 | O8806: Office Supplies | P8806: Labels | Q8806: Avery 51 | R8806: 18.9 | S8806: 3 | T8806: 0 | U8806: 8.694 | V8806: =U8806/R8806 -> 0.46
A8807: 8806 | B8807: US-2017-100398 | C8807: 42966 | D8807: 42970 | E8807: Standard Class | F8807: DO-13435 | G8807: Denny Ordway | H8807: Consumer | I8807: United States | J8807: Salt Lake City | K8807: Utah | L8807: 84106 | M8807: West | N8807: OFF-BI-10002133 | O8807: Office Supplies | P8807: Binders | Q8807: Wilson Jones Elliptical Ring 3 1/2" Capacity Binders, 800 sheets | R8807: 102.72 | S8807: 3 | T8807: 0.2 | U8807: 37.236 | V8807: =U8807/R8807 -> 0.3625
A8808: 8807 | B8808: CA-2016-113082 | C8808: 42625 | D8808: 42629 | E8808: Standard Class | F8808: MC-17590 | G8808: Matt Collister | H8808: Corporate | I8808: United States | J8808: Utica | K8808: New York | L8808: 13501 | M8808: East | N8808: FUR-FU-10002813 | O8808: Furniture | P8808: Furnishings | Q8808: DAX Contemporary Wood Frame with Silver Metal Mat, Desktop, 11 x 14 Size | R8808: 40.48 | S8808: 2 | T8808: 0 | U8808: 14.5728 | V8808: =U8808/R8808 -> 0.36
A8809: 8808 | B8809: US-2017-110646 | C8809: 43034 | D8809: 43039 | E8809: Standard Class | F8809: JF-15190 | G8809: Jamie Frazer | H8809: Consumer | I8809: United States | J8809: Philadelphia | K8809: Pennsylvania | L8809: 19134 | M8809: East | N8809: OFF-BI-10004330 | O8809: Office Supplies | P8809: Binders | Q8809: GBC Velobind Prepunched Cover Sets, Regency Series | R8809: 33.282 | S8809: 3 | T8809: 0.7 | U8809: -27.735 | V8809: =U8809/R8809 -> -0.83333333
A8810: 8809 | B8810: US-2017-110646 | C8810: 43034 | D8810: 43039 | E8810: Standard Class | F8810: JF-15190 | G8810: Jamie Frazer | H8810: Consumer | I8810: United States | J8810: Philadelphia | K8810: Pennsylvania | L8810: 19134 | M8810: East | N8810: TEC-PH-10002807 | O8810: Technology | P8810: Phones | Q8810: Motorla HX550 Universal Bluetooth Headset | R8810: 118.65 | S8810: 5 | T8810: 0.4 | U8810: 19.775 | V8810: =U8810/R8810 -> 0.16666667
A8811: 8810 | B8811: US-2017-110646 | C8811: 43034 | D8811: 43039 | E8811: Standard Class | F8811: JF-15190 | G8811: Jamie Frazer | H8811: Consumer | I8811: United States | J8811: Philadelphia | K8811: Pennsylvania | L8811: 19134 | M8811: East | N8811: OFF-LA-10001404 | O8811: Office Supplies | P8811: Labels | Q8811: Avery 517 | R8811: 14.76 | S8811: 5 | T8811: 0.2 | U8811: 4.9815 | V8811: =U8811/R8811 -> 0.3375
A8812: 8811 | B8812: CA-2017-120614 | C8812: 42885 | D8812: 42890 | E8812: Standard Class | F8812: SM-20950 | G8812: Suzanne McNair | H8812: Corporate | I8812: United States | J8812: Los Angeles | K8812: California | L8812: 90004 | M8812: West | N8812: OFF-PA-10004911 | O8812: Office Supplies | P8812: Paper | Q8812: Rediform S.O.S. 1-Up Phone Message Bk, 4-1/4x3-1/16 Bk, 1 Form/Pg, 40 Messages/Bk, 3/Pk | R8812: 37.52 | S8812: 4 | T8812: 0 | U8812: 18.0096 | V8812: =U8812/R8812 -> 0.48
... A9147: 9146 | B9147: CA-2015-126970 | C9147: 42267 | D9147: 42271 | E9147: Standard Class | F9147: TP-21130 | G9147: Theone Pippenger | H9147: Consumer | I9147: United States | J9147: Naperville | K9147: Illinois | L9147: 60540 | M9147: Central | N9147: OFF-BI-10000138 | O9147: Office Supplies | P9147: Binders | Q9147: Acco Translucent Poly Ring Binders | R9147: 2.808 | S9147: 3 | T9147: 0.8 | U9147: -4.4928 | V9147: =U9147/R9147 -> -1.6
A9148: 9147 | B9148: US-2016-165505 | C9148: 42392 | D9148: 42396 | E9148: Standard Class | F9148: CB-12535 | G9148: Claudia Bergmann | H9148: Corporate | I9148: United States | J9148: Burlington | K9148: Vermont | L9148: 05408 | M9148: East | N9148: TEC-AC-10002926 | O9148: Technology | P9148: Accessories | Q9148: Logitech Wireless Marathon Mouse M705 | R9148: 99.98 | S9148: 2 | T9148: 0 | U9148: 42.9914 | V9148: =U9148/R9148 -> 0.43
A9149: 9148 | B9149: US-2016-165505 | C9149: 42392 | D9149: 42396 | E9149: Standard Class | F9149: CB-12535 | G9149: Claudia Bergmann | H9149: Corporate | I9149: United States | J9149: Burlington | K9149: Vermont | L9149: 05408 | M9149: East | N9149: OFF-AR-10003477 | O9149: Office Supplies | P9149: Art | Q9149: 4009 Highlighters | R9149: 8.04 | S9149: 6 | T9149: 0 | U9149: 2.7336 | V9149: =U9149/R9149 -> 0.34
A9150: 9149 | B9150: US-2016-165505 | C9150: 42392 | D9150: 42396 | E9150: Standard Class | F9150: CB-12535 | G9150: Claudia Bergmann | H9150: Corporate | I9150: United States | J9150: Burlington | K9150: Vermont | L9150: 05408 | M9150: East | N9150: OFF-ST-10001526 | O9150: Office Supplies | P9150: Storage | Q9150: Iceberg Mobile Mega Data/Printer Cart | R9150: 1564.29 | S9150: 13 | T9150: 0 | U9150: 406.7154 | V9150: =U9150/R9150 -> 0.26
A9151: 9150 | B9151: US-2014-157070 | C9151: 41791 | D9151: 41796 | E9151: Standard Class | F9151: QJ-19255 | G9151: Quincy Jones | H9151: Corporate | I9151: United States | J9151: Detroit | K9151: Michigan | L9151: 48234 | M9151: Central | N9151: OFF-BI-10001765 | O9151: Office Supplies | P9151: Binders | Q9151: Wilson Jones Heavy-Duty Casebound Ring Binders with Metal Hinges | R9151: 138.56 | S9151: 4 | T9151: 0 | U9151: 66.5088 | V9151: =U9151/R9151 -> 0.48
A9152: 9151 | B9152: US-2014-157070 | C9152: 41791 | D9152: 41796 | E9152: Standard Class | F9152: QJ-19255 | G9152: Quincy Jones | H9152: Corporate | I9152: United States | J9152: Detroit | K9152: Michigan | L9152: 48234 | M9152: Central | N9152: OFF-AP-10004859 | O9152: Office Supplies | P9152: Appliances | Q9152: Acco 6 Outlet Guardian Premium Surge Suppressor | R9152: 65.52 | S9152: 5 | T9152: 0.1 | U9152: 12.376 | V9152: =U9152/R9152 -> 0.18888889
A9153: 9152 | B9153: US-2015-106873 | C9153: 42271 | D9153: 42276 | E9153: Second Class | F9153: KM-16720 | G9153: Kunst Miller | H9153: Consumer | I9153: United States | J9153: Avondale | K9153: Arizona | L9153: 85323 | M9153: West | N9153: OFF-AR-10003179 | O9153: Office Supplies | P9153: Art | Q9153: Dixon Ticonderoga Core-Lock Colored Pencils | R9153: 14.576 | S9153: 2 | T9153: 0.2 | U9153: 2.3686 | V9153: =U9153/R9153 -> 0.1625
A9154: 9153 | B9154: US-2015-106873 | C9154: 42271 | D9154: 42276 | E9154: Second Class | F9154: KM-16720 | G9154: Kunst Miller | H9154: Consumer | I9154: United States | J9154: Avondale | K9154: Arizona | L9154: 85323 | M9154: West | N9154: TEC-AC-10002345 | O9154: Technology | P9154: Accessories | Q9154: HP Standard 104 key PS/2 Keyboard | R9154: 23.2 | S9154: 2 | T9154: 0.2 | U9154: 1.45 | V9154: =U9154/R9154 -> 0.0625
A9155: 9154 | B9155: US-2015-106873 | C9155: 42271 | D9155: 42276 | E9155: Second Class | F9155: KM-16720 | G9155: Kunst Miller | H9155: Consumer | I9155: United States | J9155: Avondale | K9155: Arizona | L9155: 85323 | M9155: West | N9155: OFF-AR-10001246 | O9155: Office Supplies | P9155: Art | Q9155: Newell 317 | R9155: 16.464 | S9155: 7 | T9155: 0.2 | U9155: 1.8522 | V9155: =U9155/R9155 -> 0.1125
A9156: 9155 | B9156: CA-2016-132990 | C9156: 42583 | D9156: 42585 | E9156: Second Class | F9156: KM-16660 | G9156: Khloe Miller | H9156: Consumer | I9156: United States | J9156: Philadelphia | K9156: Pennsylvania | L9156: 19140 | M9156: East | N9156: FUR-FU-10004864 | O9156: Furniture | P9156: Furnishings | Q9156: Eldon 500 Class Desk Accessories | R9156: 19.312 | S9156: 2 | T9156: 0.2 | U9156: 3.1382 | V9156: =U9156/R9156 -> 0.1625
A9157: 9156 | B9157: CA-2014-102645 | C9157: 41662 | D9157: 41667 | E9157: Standard Class | F9157: IM-15055 | G9157: Ionia McGrath | H9157: Consumer | I9157: United States | J9157: Las Vegas | K9157: Nevada | L9157: 89115 | M9157: West | N9157: OFF-PA-10001804 | O9157: Office Supplies | P9157: Paper | Q9157: Xerox 195 | R9157: 40.08 | S9157: 6 | T9157: 0 | U9157: 19.2384 | V9157: =U9157/R9157 -> 0.48
A9158: 9157 | B9158: CA-2014-134215 | C9158: 41855 | D9158: 41859 | E9158: Standard Class | F9158: ML-17395 | G9158: Marina Lichtenstein | H9158: Corporate | I9158: United States | J9158: Bangor | K9158: Maine | L9158: 4401 | M9158: East | N9158: OFF-AP-10001271 | O9158: Office Supplies | P9158: Appliances | Q9158: Eureka The Boss Cordless Rechargeable Stick Vac | R9158: 101.96 | S9158: 2 | T9158: 0 | U9158: 27.5292 | V9158: =U9158/R9158 -> 0.27
A9159: 9158 | B9159: CA-2014-134215 | C9159: 41855 | D9159: 41859 | E9159: Standard Class | F9159: ML-17395 | G9159: Marina Lichtenstein | H9159: Corporate | I9159: United States | J9159: Bangor | K9159: Maine | L9159: 4401 | M9159: East | N9159: OFF-PA-10004353 | O9159: Office Supplies | P9159: Paper | Q9159: Southworth 25% Cotton Premium Laser Paper and Envelopes | R9159: 259.74 | S9159: 13 | T9159: 0 | U9159: 124.6752 | V9159: =U9159/R9159 -> 0.48
A9160: 9159 | B9160: CA-2014-134215 | C9160: 41855 | D9160: 41859 | E9160: Standard Class | F9160: ML-17395 | G9160: Marina Lichtenstein | H9160: Corporate | I9160: United States | J9160: Bangor | K9160: Maine | L9160: 4401 | M9160: East | N9160: TEC-AC-10002473 | O9160: Technology | P9160: Accessories | Q9160: Maxell 4.7GB DVD-R | R9160: 255.42 | S9160: 9 | T9160: 0 | U9160: 104.7222 | V9160: =U9160/R9160 -> 0.41
A9161: 9160 | B9161: CA-2016-118934 | C9161: 42591 | D9161: 42596 | E9161: Standard Class | F9161: GH-14410 | G9161: Gary Hansen | H9161: Home Office | I9161: United States | J9161: Hendersonville | K9161: Tennessee | L9161: 37075 | M9161: South | N9161: OFF-BI-10003314 | O9161: Office Supplies | P9161: Binders | Q9161: Tuff Stuff Recycled Round Ring Binders | R9161: 4.338 | S9161: 3 | T9161: 0.7 | U9161: -3.0366 | V9161: =U9161/R9161 -> -0.7
A9162: 9161 | B9162: CA-2016-118934 | C9162: 42591 | D9162: 42596 | E9162: Standard Class | F9162: GH-14410 | G9162: Gary Hansen | H9162: Home Office | I9162: United States | J9162: Hendersonville | K9162: Tennessee | L9162: 37075 | M9162: South | N9162: OFF-BI-10004465 | O9162: Office Supplies | P9162: Binders | Q9162: Avery Durable Slant Ring Binders | R9162: 11.88 | S9162: 5 | T9162: 0.7 | U9162: -7.92 | V9162: =U9162/R9162 -> -0.66666667
... A9387: 9386 | B9387: CA-2017-163097 | C9387: 42974 | D9387: 42978 | E9387: Standard Class | F9387: SF-20200 | G9387: Sarah Foster | H9387: Consumer | I9387: United States | J9387: Mesa | K9387: Arizona | L9387: 85204 | M9387: West | N9387: FUR-FU-10004973 | O9387: Furniture | P9387: Furnishings | Q9387: Flat Face Poster Frame | R9387: 120.576 | S9387: 8 | T9387: 0.2 | U9387: 33.1584 | V9387: =U9387/R9387 -> 0.275
A9388: 9387 | B9388: US-2017-127292 | C9388: 42754 | D9388: 42758 | E9388: Standard Class | F9388: RM-19375 | G9388: Raymond Messe | H9388: Consumer | I9388: United States | J9388: Burlington | K9388: Vermont | L9388: 05408 | M9388: East | N9388: OFF-PA-10000157 | O9388: Office Supplies | P9388: Paper | Q9388: Xerox 191 | R9388: 79.92 | S9388: 4 | T9388: 0 | U9388: 37.5624 | V9388: =U9388/R9388 -> 0.47
A9389: 9388 | B9389: US-2017-127292 | C9389: 42754 | D9389: 42758 | E9389: Standard Class | F9389: RM-19375 | G9389: Raymond Messe | H9389: Consumer | I9389: United States | J9389: Burlington | K9389: Vermont | L9389: 05408 | M9389: East | N9389: OFF-PA-10001970 | O9389: Office Supplies | P9389: Paper | Q9389: Xerox 1881 | R9389: 12.28 | S9389: 1 | T9389: 0 | U9389: 5.7716 | V9389: =U9389/R9389 -> 0.47
A9390: 9389 | B9390: US-2017-127292 | C9390: 42754 | D9390: 42758 | E9390: Standard Class | F9390: RM-19375 | G9390: Raymond Messe | H9390: Consumer | I9390: United States | J9390: Burlington | K9390: Vermont | L9390: 05408 | M9390: East | N9390: OFF-AP-10000828 | O9390: Office Supplies | P9390: Appliances | Q9390: Avanti 4.4 Cu. Ft. Refrigerator | R9390: 542.94 | S9390: 3 | T9390: 0 | U9390: 152.0232 | V9390: =U9390/R9390 -> 0.28
A9391: 9390 | B9391: US-2017-127292 | C9391: 42754 | D9391: 42758 | E9391: Standard Class | F9391: RM-19375 | G9391: Raymond Messe | H9391: Consumer | I9391: United States | J9391: Burlington | K9391: Vermont | L9391: 05408 | M9391: East | N9391: OFF-EN-10001509 | O9391: Office Supplies | P9391: Envelopes | Q9391: Poly String Tie Envelopes | R9391: 2.04 | S9391: 1 | T9391: 0 | U9391: 0.9588 | V9391: =U9391/R9391 -> 0.47
A9392: 9391 | B9392: CA-2015-163734 | C9392: 42174 | D9392: 42179 | E9392: Standard Class | F9392: KM-16375 | G9392: Katherine Murray | H9392: Home Office | I9392: United States | J9392: Houston | K9392: Texas | L9392: 77070 | M9392: Central | N9392: OFF-ST-10003692 | O9392: Office Supplies | P9392: Storage | Q9392: Recycled Steel Personal File for Hanging File Folders | R9392: 228.92 | S9392: 5 | T9392: 0.2 | U9392: 14.3075 | V9392: =U9392/R9392 -> 0.0625
A9393: 9392 | B9393: CA-2017-162474 | C9393: 42807 | D9393: 42810 | E9393: First Class | F9393: FH-14275 | G9393: Frank Hawley | H9393: Corporate | I9393: United States | J9393: Aurora | K9393: Illinois | L9393: 60505 | M9393: Central | N9393: TEC-PH-10004700 | O9393: Technology | P9393: Phones | Q9393: PowerGen Dual USB Car Charger | R9393: 7.992 | S9393: 1 | T9393: 0.2 | U9393: 2.5974 | V9393: =U9393/R9393 -> 0.325
A9394: 9393 | B9394: CA-2015-130848 | C9394: 42302 | D9394: 42302 | E9394: Same Day | F9394: DG-13300 | G9394: Deirdre Greer | H9394: Corporate | I9394: United States | J9394: Denver | K9394: Colorado | L9394: 80219 | M9394: West | N9394: FUR-CH-10000422 | O9394: Furniture | P9394: Chairs | Q9394: Global Highback Leather Tilter in Burgundy | R9394: 582.336 | S9394: 8 | T9394: 0.2 | U9394: -29.1168 | V9394: =U9394/R9394 -> -0.05
A9395: 9394 | B9395: CA-2014-125997 | C9395: 41902 | D9395: 41905 | E9395: First Class | F9395: MW-18220 | G9395: Mitch Webber | H9395: Consumer | I9395: United States | J9395: New York City | K9395: New York | L9395: 10011 | M9395: East | N9395: TEC-PH-10003484 | O9395: Technology | P9395: Phones | Q9395: Ooma Telo VoIP Home Phone System | R9395: 629.95 | S9395: 5 | T9395: 0 | U9395: 157.4875 | V9395: =U9395/R9395 -> 0.25
A9396: 9395 | B9396: CA-2014-125997 | C9396: 41902 | D9396: 41905 | E9396: First Class | F9396: MW-18220 | G9396: Mitch Webber | H9396: Consumer | I9396: United States | J9396: New York City | K9396: New York | L9396: 10011 | M9396: East | N9396: FUR-CH-10001394 | O9396: Furniture | P9396: Chairs | Q9396: Global Leather Executive Chair | R9396: 631.782 | S9396: 2 | T9396: 0.1 | U9396: 140.396 | V9396: =U9396/R9396 -> 0.22222222
A9397: 9396 | B9397: CA-2014-125997 | C9397: 41902 | D9397: 41905 | E9397: First Class | F9397: MW-18220 | G9397: Mitch Webber | H9397: Consumer | I9397: United States | J9397: New York City | K9397: New York | L9397: 10011 | M9397: East | N9397: FUR-BO-10002213 | O9397: Furniture | P9397: Bookcases | Q9397: DMI Eclipse Executive Suite Bookcases | R9397: 801.568 | S9397: 2 | T9397: 0.2 | U9397: -10.0196 | V9397: =U9397/R9397 -> -0.0125
A9398: 9397 | B9398: CA-2014-125997 | C9398: 41902 | D9398: 41905 | E9398: First Class | F9398: MW-18220 | G9398: Mitch Webber | H9398: Consumer | I9398: United States | J9398: New York City | K9398: New York | L9398: 10011 | M9398: East | N9398: OFF-LA-10002762 | O9398: Office Supplies | P9398: Labels | Q9398: Avery 485 | R9398: 75.18 | S9398: 6 | T9398: 0 | U9398: 35.3346 | V9398: =U9398/R9398 -> 0.47
A9399: 9398 | B9399: CA-2014-125997 | C9399: 41902 | D9399: 41905 | E9399: First Class | F9399: MW-18220 | G9399: Mitch Webber | H9399: Consumer | I9399: United States | J9399: New York City | K9399: New York | L9399: 10011 | M9399: East | N9399: OFF-AP-10003842 | O9399: Office Supplies | P9399: Appliances | Q9399: Euro-Pro Shark Turbo Vacuum | R9399: 30.98 | S9399: 1 | T9399: 0 | U9399: 8.0548 | V9399: =U9399/R9399 -> 0.26
A9400: 9399 | B9400: CA-2014-125997 | C9400: 41902 | D9400: 41905 | E9400: First Class | F9400: MW-18220 | G9400: Mitch Webber | H9400: Consumer | I9400: United States | J9400: New York City | K9400: New York | L9400: 10011 | M9400: East | N9400: TEC-PH-10003072 | O9400: Technology | P9400: Phones | Q9400: Panasonic KX-TG9541B DECT 6.0 Digital 2-Line Expandable Cordless Phone With Digital Answering System | R9400: 1349.91 | S9400: 9 | T9400: 0 | U9400: 661.4559 | V9400: =U9400/R9400 -> 0.49
A9401: 9400 | B9401: CA-2016-103128 | C9401: 42685 | D9401: 42689 | E9401: Standard Class | F9401: SC-20845 | G9401: Sung Chung | H9401: Consumer | I9401: United States | J9401: Arlington Heights | K9401: Illinois | L9401: 60004 | M9401: Central | N9401: OFF-AR-10003394 | O9401: Office Supplies | P9401: Art | Q9401: Newell 332 | R9401: 14.112 | S9401: 6 | T9401: 0.2 | U9401: 1.2348 | V9401: =U9401/R9401 -> 0.0875
A9402: 9401 | B9402: CA-2015-167696 | C9402: 42263 | D9402: 42268 | E9402: Standard Class | F9402: BD-11500 | G9402: Bradley Drucker | H9402: Consumer | I9402: United States | J9402: Newport News | K9402: Virginia | L9402: 23602 | M9402: South | N9402: OFF-EN-10001539 | O9402: Office Supplies | P9402: Envelopes | Q9402: Staple envelope | R9402: 31.12 | S9402: 4 | T9402: 0 | U9402: 14.6264 | V9402: =U9402/R9402 -> 0.47
A9403: 9402 | B9403: CA-2014-159814 | C9403: 41814 | D9403: 41818 | E9403: Standard Class | F9403: LP-17080 | G9403: Liz Pelletier | H9403: Consumer | I9403: United States | J9403: Tucson | K9403: Arizona | L9403: 85705 | M9403: West | N9403: FUR-FU-10001731 | O9403: Furniture | P9403: Furnishings | Q9403: Acrylic Self-Standing Desk Frames | R9403: 4.272 | S9403: 2 | T9403: 0.2 | U9403: 0.9612 | V9403: =U9403/R9403 -> 0.225
... A9742: 9741 | B9742: CA-2017-129294 | C9742: 42810 | D9742: 42815 | E9742: Standard Class | F9742: KD-16615 | G9742: Ken Dana | H9742: Corporate | I9742: United States | J9742: Los Angeles | K9742: California | L9742: 90032 | M9742: West | N9742: OFF-AP-10001154 | O9742: Office Supplies | P9742: Appliances | Q9742: Bionaire Personal Warm Mist Humidifier/Vaporizer | R9742: 140.67 | S9742: 3 | T9742: 0 | U9742: 54.8613 | V9742: =U9742/R9742 -> 0.39
A9743: 9742 | B9743: CA-2015-117086 | C9743: 42316 | D9743: 42320 | E9743: Standard Class | F9743: QJ-19255 | G9743: Quincy Jones | H9743: Corporate | I9743: United States | J9743: Burlington | K9743: Vermont | L9743: 05408 | M9743: East | N9743: FUR-BO-10004834 | O9743: Furniture | P9743: Bookcases | Q9743: Riverside Palais Royal Lawyers Bookcase, Royale Cherry Finish | R9743: 4404.9 | S9743: 5 | T9743: 0 | U9743: 1013.127 | V9743: =U9743/R9743 -> 0.23
A9744: 9743 | B9744: CA-2017-131303 | C9744: 43067 | D9744: 43071 | E9744: Standard Class | F9744: EP-13915 | G9744: Emily Phan | H9744: Consumer | I9744: United States | J9744: San Diego | K9744: California | L9744: 92037 | M9744: West | N9744: OFF-LA-10001074 | O9744: Office Supplies | P9744: Labels | Q9744: Round Specialty Laser Printer Labels | R9744: 62.65 | S9744: 5 | T9744: 0 | U9744: 29.4455 | V9744: =U9744/R9744 -> 0.47
A9745: 9744 | B9745: CA-2016-137127 | C9745: 42537 | D9745: 42543 | E9745: Standard Class | F9745: JJ-15445 | G9745: Jennifer Jackson | H9745: Consumer | I9745: United States | J9745: Newark | K9745: Delaware | L9745: 19711 | M9745: East | N9745: OFF-LA-10001641 | O9745: Office Supplies | P9745: Labels | Q9745: Avery 518 | R9745: 9.45 | S9745: 3 | T9745: 0 | U9745: 4.536 | V9745: =U9745/R9745 -> 0.48
A9746: 9745 | B9746: CA-2017-141782 | C9746: 42756 | D9746: 42760 | E9746: Standard Class | F9746: BE-11410 | G9746: Bobby Elias | H9746: Consumer | I9746: United States | J9746: Aurora | K9746: Illinois | L9746: 60505 | M9746: Central | N9746: OFF-EN-10002230 | O9746: Office Supplies | P9746: Envelopes | Q9746: Airmail Envelopes | R9746: 268.576 | S9746: 4 | T9746: 0.2 | U9746: 90.6444 | V9746: =U9746/R9746 -> 0.3375
A9747: 9746 | B9747: CA-2017-137505 | C9747: 43063 | D9747: 43063 | E9747: Same Day | F9747: BP-11290 | G9747: Beth Paige | H9747: Consumer | I9747: United States | J9747: Los Angeles | K9747: California | L9747: 90008 | M9747: West | N9747: FUR-TA-10000617 | O9747: Furniture | P9747: Tables | Q9747: Hon Practical Foundations 30 x 60 Training Table, Light Gray/Charcoal | R9747: 364.08 | S9747: 2 | T9747: 0.2 | U9747: 9.102 | V9747: =U9747/R9747 -> 0.025
A9748: 9747 | B9748: CA-2017-137505 | C9748: 43063 | D9748: 43063 | E9748: Same Day | F9748: BP-11290 | G9748: Beth Paige | H9748: Consumer | I9748: United States | J9748: Los Angeles | K9748: California | L9748: 90008 | M9748: West | N9748: FUR-TA-10001676 | O9748: Furniture | P9748: Tables | Q9748: Hon 61000 Series Interactive Training Tables | R9748: 71.088 | S9748: 2 | T9748: 0.2 | U9748: -1.7772 | V9748: =U9748/R9748 -> -0.025
A9749: 9748 | B9749: US-2014-140914 | C9749: 41954 | D9749: 41958 | E9749: Standard Class | F9749: BH-11710 | G9749: Brosina Hoffman | H9749: Consumer | I9749: United States | J9749: Chicago | K9749: Illinois | L9749: 60653 | M9749: Central | N9749: FUR-FU-10000175 | O9749: Furniture | P9749: Furnishings | Q9749: DAX Wood Document Frame. | R9749: 10.984 | S9749: 2 | T9749: 0.6 | U9749: -7.9634 | V9749: =U9749/R9749 -> -0.725
A9750: 9749 | B9750: US-2014-140914 | C9750: 41954 | D9750: 41958 | E9750: Standard Class | F9750: BH-11710 | G9750: Brosina Hoffman | H9750: Consumer | I9750: United States | J9750: Chicago | K9750: Illinois | L9750: 60653 | M9750: Central | N9750: FUR-CH-10003379 | O9750: Furniture | P9750: Chairs | Q9750: Global Commerce Series High-Back Swivel/Tilt Chairs | R9750: 797.944 | S9750: 4 | T9750: 0.3 | U9750: -56.996 | V9750: =U9750/R9750 -> -0.071428571
A9751: 9750 | B9751: CA-2016-158358 | C9751: 42433 | D9751: 42437 | E9751: Standard Class | F9751: EM-13810 | G9751: Eleni McCrary | H9751: Corporate | I9751: United States | J9751: Dover | K9751: New Hampshire | L9751: 3820 | M9751: East | N9751: TEC-AC-10002567 | O9751: Technology | P9751: Accessories | Q9751: Logitech G602 Wireless Gaming Mouse | R9751: 159.98 | S9751: 2 | T9751: 0 | U9751: 57.5928 | V9751: =U9751/R9751 -> 0.36
A9752: 9751 | B9752: CA-2016-113390 | C9752: 42654 | D9752: 42658 | E9752: Standard Class | F9752: EP-13915 | G9752: Emily Phan | H9752: Consumer | I9752: United States | J9752: Chicago | K9752: Illinois | L9752: 60610 | M9752: Central | N9752: OFF-AR-10003183 | O9752: Office Supplies | P9752: Art | Q9752: Avery Fluorescent Highlighter Four-Color Set | R9752: 5.344 | S9752: 2 | T9752: 0.2 | U9752: 0.668 | V9752: =U9752/R9752 -> 0.125
A9753: 9752 | B9753: CA-2016-113390 | C9753: 42654 | D9753: 42658 | E9753: Standard Class | F9753: EP-13915 | G9753: Emily Phan | H9753: Consumer | I9753: United States | J9753: Chicago | K9753: Illinois | L9753: 60610 | M9753: Central | N9753: OFF-AR-10001446 | O9753: Office Supplies | P9753: Art | Q9753: Newell 309 | R9753: 27.72 | S9753: 3 | T9753: 0.2 | U9753: 3.465 | V9753: =U9753/R9753 -> 0.125
...

Sheet Sheet1

Sheet Sheet2
A2: Claire Gute
A3: Darrin Van Huff
A4: Sean O'Donnell
A5: Brosina Hoffman
A6: Andrew Allen
A7: Irene Maddox
A8: Harold Pawlan
A9: Pete Kriz
A10: Alejandro Grove
A11: Zuschuss Donatelli
A12: Ken Black
A13: Sandra Flanagan
... A794: Susan MacKendrick

Sheet Dashboard
A1: Super Store Sales - Dashboard
A4: Total Sales: | B4: =SUM(Orders!R321:'Orders'!R9995) -> 2213541.1 | D4: Sum of Sales | K4: Sum of Sales
A5: Total Profit: | B5: =SUM(Orders!U2:'Orders'!U9995) -> 286397.02 | D5: Category | E5: Total | K5: Years | L5: Quarters | M5: Order Date | N5: Total
A6: Total Quantity: | B6: =SUM(Orders!S2:'Orders'!S9995) -> 37873 | D6: Technology | E6: 836154.03 | K6: 2014 | L6: Qtr1 | M6: Jan | N6: 14236.895
A7: Profit Per Order: | B7: =B5/COUNTA(Orders!B2:'Orders'!B9995) -> 28.656896 | D7: Furniture | E7: 741999.8 | M7: Feb | N7: 4519.892 | Z7: 132.4 | AA7: 13059.144
A8: Total Profit Margin: | B8: =SUM(Orders!V2:'Orders'!V9995) -> 1202.4174 | D8: Office Supplies | E8: 719047.03 | M8: Mar | N8: 55691.009 | Z8: 105 | AA8: 26590.166
A9: Total Customer: | B9: =793 -> 793 | D9: Grand Total | E9: 2297200.9 | L9: Qtr2 | M9: Apr | N9: 28295.345 | Z9: 83.35 | AA9: -17725.481
M10: May | N10: 23648.287 | Z10: 48.14 | AA10: -3472.556
M11: Jun | N11: 34595.128 | Z11: 368.89 | AA11: 18451.273
A12: Sum of Sales | L12: Qtr3 | M12: Jul | N12: 33946.393 | Z12: 567 | AA12: 30221.763
A13: Ship Mode | B13: Total | M13: Aug | N13: 27909.468 | Z13: 102.6 | AA13: 34053.569
A14: First Class | B14: 351428.42 | M14: Sep | N14: 81777.351 | Z14: 77.6 | AA14: 18138.005
A15: Same Day | B15: 128363.12 | L15: Qtr4 | M15: Oct | N15: 31453.393 | Z15: 63.2 | AA15: 21278.826
A16: Second Class | B16: 459193.57 | D16: Sum of Sales | M16: Nov | N16: 78628.717 | Z16: 59.6 | AA16: 6527.787
A17: Standard Class | B17: 1358215.7 | D17: Region | E17: Total | M17: Dec | N17: 69545.62 | Z17: 25 | AA17: 5546.254
A18: Grand Total | B18: 2297200.9 | D18: West | E18: 725457.82 | K18: 2015 | L18: Qtr1 | M18: Jan | N18: 18174.076 | Z18: 20.4 | AA18: 6964.1767
D19: East | E19: 678781.24 | M19: Feb | N19: 11951.411 | Q19: Data | Z19: 17.8 | AA19: 949.5182
D20: Central | E20: 501239.89 | M20: Mar | N20: 38726.252 | P20: Category | Q20: Sum of Sales | R20: Sum of Profit | Z20: 14.6 | AA20: -1189.0995
D21: South | E21: 391721.91 | L21: Qtr2 | M21: Apr | N21: 34195.208 | P21: Technology | Q21: 836154.03 | R21: 145454.95 | Z21: 947.8 | AA21: 122490.8
D22: Grand Total | E22: 2297200.9 | M22: May | N22: 30131.686 | P22: Furniture | Q22: 741999.8 | R22: 18451.273 | Z22: 137.4 | AA22: 44515.731
M23: Jun | N23: 24797.292 | P23: Office Supplies | Q23: 719047.03 | R23: 122490.8 | Z23: 60.8 | AA23: 41936.636
L24: Qtr3 | M24: Jul | N24: 28765.325 | P24: Grand Total | Q24: 2297200.9 | R24: 286397.02 | Z24: 35.2 | AA24: 3384.7569
M25: Aug | N25: 36898.332 | Z25: 11 | AA25: 55617.825
M26: Sep | N26: 64595.918 | Z26: 244.4 | AA26: 145454.95
D27: Sum of Sales | L27: Qtr4 | M27: Oct | N27: 31404.924
D28: Segment | E28: Total | M28: Nov | N28: 75972.564
D29: Consumer | E29: 1161401.3 | M29: Dec | N29: 74919.521
D30: Corporate | E30: 706146.37 | K30: 2016 | L30: Qtr1 | M30: Jan | N30: 18542.491 | AA30: Sum of Profit
D31: Home Office | E31: 429653.15 | M31: Feb | N31: 22978.815 | AA31: Years | AB31: Quarters | AC31: Order Date | AD31: Total
D32: Grand Total | E32: 2297200.9 | M32: Mar | N32: 51715.875 | Q32: Data | AA32: 2014 | AB32: Qtr1 | AC32: Jan | AD32: 2450.1907
L33: Qtr2 | M33: Apr | N33: 38750.039 | P33: Region | Q33: Sum of Sales | R33: Sum of Profit | AC33: Feb | AD33: 862.3084
M34: May | N34: 56987.728 | P34: West | Q34: 725457.82 | R34: 108418.45 | AC34: Mar | AD34: 498.7299
M35: Jun | N35: 40344.534 | P35: East | Q35: 678781.24 | R35: 91522.78 | AB35: Qtr2 | AC35: Apr | AD35: 3488.8352
L36: Qtr3 | M36: Jul | N36: 39261.963 | P36: Central | Q36: 501239.89 | R36: 39706.362 | AC36: May | AD36: 2738.7096
M37: Aug | N37: 31115.374 | P37: South | Q37: 391721.91 | R37: 46749.43 | AC37: Jun | AD37: 4976.5244
M38: Sep | N38: 73410.025 | P38: Grand Total | Q38: 2297200.9 | R38: 286397.02 | AB38: Qtr3 | AC38: Jul | AD38: -841.4826
A39: Sum of Sales | L39: Qtr4 | M39: Oct | N39: 59687.745 | AC39: Aug | AD39: 5318.105
A40: Sub-Category | B40: Total | M40: Nov | N40: 79411.966 | AC40: Sep | AD40: 8328.0994
A41: Phones | B41: 330007.05 | M41: Dec | N41: 96999.043 | AB41: Qtr4 | AC41: Oct | AD41: 3448.2573
A42: Chairs | B42: 328449.1 | K42: 2017 | L42: Qtr1 | M42: Jan | N42: 43971.374 | AC42: Nov | AD42: 9292.1269
A43: Storage | B43: 223843.61 | M43: Feb | N43: 20301.133 | AC43: Dec | AD43: 8983.5699
A44: Tables | B44: 206965.53 | M44: Mar | N44: 58872.353 | AA44: 2015 | AB44: Qtr1 | AC44: Jan | AD44: -3281.007
A45: Binders | B45: 203412.73 | L45: Qtr2 | M45: Apr | N45: 36521.536 | AC45: Feb | AD45: 2813.8508
A46: Machines | B46: 189238.63 | M46: May | N46: 44261.11 | R46: Data | AC46: Mar | AD46: 9732.0978
A47: Accessories | B47: 167380.32 | M47: Jun | N47: 52981.726 | P47: Category | Q47: Sub-Category | R47: Sum of Discount | S47: Sum of Profit | AB47: Qtr2 | AC47: Apr | AD47: 4187.4962
A48: Copiers | B48: 149528.03 | L48: Qtr3 | M48: Jul | N48: 45264.416 | P48: Furniture | Q48: Furnishings | R48: 132.4 | S48: 13059.144 | AC48: May | AD48: 4667.869
A49: Bookcases | B49: 114880 | M49: Aug | N49: 63120.888 | Q49: Chairs | R49: 105 | S49: 26590.166 | AC49: Jun | AD49: 3335.5572
A50: Appliances | B50: 107532.16 | M50: Sep | N50: 87866.652 | Q50: Tables | R50: 83.35 | S50: -17725.481 | AB50: Qtr3 | AC50: Jul | AD50: 3288.6483
A51: Furnishings | B51: 91705.164 | L51: Qtr4 | M51: Oct | N51: 77776.923 | Q51: Bookcases | R51: 48.14 | S51: -3472.556 | AC51: Aug | AD51: 5355.8084
A52: Paper | B52: 78479.206 | M52: Nov | N52: 118447.83 | P52: Furniture Total | R52: 368.89 | S52: 18451.273 | AC52: Sep | AD52: 8209.1627
A53: Supplies | B53: 46673.538 | M53: Dec | N53: 83829.319 | P53: Office Supplies | Q53: Binders | R53: 567 | S53: 30221.763 | AB53: Qtr4 | AC53: Oct | AD53: 2817.366
A54: Art | B54: 27118.792 | K54: Grand Total | N54: 2297200.9 | Q54: Paper | R54: 102.6 | S54: 34053.569 | AC54: Nov | AD54: 12474.788
A55: Envelopes | B55: 16476.402 | Q55: Appliances | R55: 77.6 | S55: 18138.005 | AC55: Dec | AD55: 8016.9659
A56: Labels | B56: 12486.312 | Q56: Storage | R56: 63.2 | S56: 21278.826 | AA56: 2016 | AB56: Qtr1 | AC56: Jan | AD56: 2824.8233
A57: Fasteners | B57: 3024.28 | Q57: Art | R57: 59.6 | S57: 6527.787 | AC57: Feb | AD57: 5004.5795
A58: Grand Total | B58: 2297200.9 | M58: Count of Customer ID | Q58: Labels | R58: 25 | S58: 5546.254 | AC58: Mar | AD58: 3611.968
M59: Segment | N59: Total | Q59: Envelopes | R59: 20.4 | S59: 6964.1767 | AB59: Qtr2 | AC59: Apr | AD59: 2977.8149
M60: Consumer | N60: 5191 | Q60: Fasteners | R60: 17.8 | S60: 949.5182 | AC60: May | AD60: 8662.1464
M61: Corporate | N61: 3020 | Q61: Supplies | R61: 14.6 | S61: -1189.0995 | AC61: Jun | AD61: 4750.3781
M62: Home Office | N62: 1783 | P62: Office Supplies Total | R62: 947.8 | S62: 122490.8 | AB62: Qtr3 | AC62: Jul | AD62: 4432.8779
M63: Grand Total | N63: 9994 | P63: Technology | Q63: Phones | R63: 137.4 | S63: 44515.731 | AC63: Aug | AD63: 2062.0693
Q64: Accessories | R64: 60.8 | S64: 41936.636 | AC64: Sep | AD64: 9328.6576
A65: Sum of Profit | G65: Sum of Profit | Q65: Machines | R65: 35.2 | S65: 3384.7569 | AB65: Qtr4 | AC65: Oct | AD65: 16243.143
A66: Category | B66: Total | G66: Region | H66: Total | Q66: Copiers | R66: 11 | S66: 55617.825 | AC66: Nov | AD66: 4011.4075
A67: Technology | B67: 145454.95 | G67: West | H67: 108418.45 | P67: Technology Total | R67: 244.4 | S67: 145454.95 | AC67: Dec | AD67: 17885.309
A68: Office Supplies | B68: 122490.8 | G68: East | H68: 91522.78 | P68: Grand Total | R68: 1561.09 | S68: 286397.02 | AA68: 2017 | AB68: Qtr1 | AC68: Jan | AD68: 7140.4391
A69: Furniture | B69: 18451.273 | G69: South | H69: 46749.43 | AC69: Feb | AD69: 1613.872
A70: Grand Total | B70: 286397.02 | G70: Central | H70: 39706.362 | AC70: Mar | AD70: 14751.891
G71: Grand Total | H71: 286397.02 | AB71: Qtr2 | AC71: Apr | AD71: 933.29
P72: Sum of Quantity | AC72: May | AD72: 6342.5828
P73: Category | Q73: Sub-Category | R73: Total | AC73: Jun | AD73: 8223.3357
P74: Furniture | Q74: Furnishings | R74: 3563 | AB74: Qtr3 | AC74: Jul | AD74: 6952.6212
Q75: Chairs | R75: 2356 | AC75: Aug | AD75: 9040.9557
Q76: Tables | R76: 1241 | AC76: Sep | AD76: 10991.556
G77: Sum of Profit | Q77: Bookcases | R77: 868 | AB77: Qtr4 | AC77: Oct | AD77: 9275.2755
A78: Sum of Profit | G78: Category | H78: Sub-Category | I78: Total | P78: Furniture Total | R78: 8028 | AC78: Nov | AD78: 9690.1037
A79: Segment | B79: Total | G79: Technology | H79: Accessories | I79: 41936.636 | P79: Office Supplies | Q79: Binders | R79: 5974 | AC79: Dec | AD79: 8483.3468
A80: Consumer | B80: 134119.21 | H80: Copiers | I80: 55617.825 | Q80: Paper | R80: 5178 | AA80: Grand Total | AD80: 286397.02
A81: Corporate | B81: 91979.134 | H81: Machines | I81: 3384.7569 | Q81: Storage | R81: 3158
A82: Home Office | B82: 60298.679 | H82: Phones | I82: 44515.731 | Q82: Art | R82: 3000
A83: Grand Total | B83: 286397.02 | G83: Technology Total | I83: 145454.95 | Q83: Appliances | R83: 1729
G84: Office Supplies | H84: Appliances | I84: 18138.005 | Q84: Labels | R84: 1400
H85: Art | I85: 6527.787 | Q85: Fasteners | R85: 914
H86: Binders | I86: 30221.763 | Q86: Envelopes | R86: 906
H87: Envelopes | I87: 6964.1767 | Q87: Supplies | R87: 647
H88: Fasteners | I88: 949.5182 | P88: Office Supplies Total | R88: 22906
H89: Labels | I89: 5546.254 | P89: Technology | Q89: Phones | R89: 3289
H90: Paper | I90: 34053.569 | Q90: Accessories | R90: 2976
H91: Storage | I91: 21278.826 | Q91: Machines | R91: 440
A92: Sum of Profit | H92: Supplies | I92: -1189.0995 | Q92: Copiers | R92: 234
A93: Ship Mode | B93: Total | G93: Office Supplies Total | I93: 122490.8 | P93: Technology Total | R93: 6939
A94: First Class | B94: 48969.84 | G94: Furniture | H94: Bookcases | I94: -3472.556 | P94: Grand Total | R94: 37873
A95: Same Day | B95: 15891.759 | H95: Chairs | I95: 26590.166
A96: Second Class | B96: 57446.635 | H96: Furnishings | I96: 13059.144
A97: Standard Class | B97: 164088.79 | H97: Tables | I97: -17725.481 | L97: Data
A98: Grand Total | B98: 286397.02 | G98: Furniture Total | I98: 18451.273 | K98: Ship Mode | L98: Sum of Sales | M98: Sum of Profit
G99: Grand Total | I99: 286397.02 | K99: Standard Class | L99: 1358215.7 | M99: 164088.79
K100: Second Class | L100: 459193.57 | M100: 57446.635
K101: First Class | L101: 351428.42 | M101: 48969.84
K102: Same Day | L102: 128363.12 | M102: 15891.759
...

Sheet Sales & Profit Dashboard
A4: No of Orders | C4: Total Sales | E4: Total Profit | G4: Profit Margin | I4: Units Sold | K4: Total Customers
A5: =COUNTA(Table1[Order ID]) -> 9994 | C5: =SUM(Table1[Sales]) -> 2297200.9 | E5: =SUM(Table1[Profit]) -> 286397.02 | G5: =E5/C5 -> 0.12467217 | I5: =SUM(Table1[Quantity]) -> 37873 | K5: =Dashboard!$B$9 -> 793

Sheet Regional base Analysis
A4: Total Regions | C4: No of Orders
A5: =COUNTA(_xlfn.UNIQUE(Table1[Region])) -> 4 | C5: =COUNTA(Table1[Order ID]) -> 9994

Sheet Ship Mode base Analysis

Sheet Returns
A1: Returned | B1: Order ID
A2: Yes | B2: CA-2017-153822
A3: Yes | B3: CA-2017-129707
A4: Yes | B4: CA-2014-152345
A5: Yes | B5: CA-2015-156440
A6: Yes | B6: US-2017-155999
A7: Yes | B7: CA-2014-157924
A8: Yes | B8: CA-2017-131807
A9: Yes | B9: CA-2016-124527
A10: Yes | B10: CA-2017-135692
A11: Yes | B11: CA-2014-123225
A12: Yes | B12: CA-2017-145772
... A297: Yes | B297: CA-2015-149636

Sheet Customer Segment analysis
A4: Total Customers
A5: =COUNTA(_xlfn.UNIQUE(Table1[Customer ID])) -> 793

Sheet People
A1: Person | B1: Region
A2: Anna Andreadi | B2: West
A3: Chuck Magee | B3: East
A4: Kelly Williams | B4: Central
A5: Cassandra Brandow | B5: South
